<?xml version="1.0" encoding="utf-8"?>
<key id="dd739acb-c6fc-4129-af98-1b92a4c091de" version="1">
  <creationDate>2021-04-28T06:01:17.2452473Z</creationDate>
  <activationDate>2021-04-28T06:01:17.1302275Z</activationDate>
  <expirationDate>2021-07-27T06:01:17.1302275Z</expirationDate>
  <descriptor deserializerType="Microsoft.AspNetCore.DataProtection.AuthenticatedEncryption.ConfigurationModel.AuthenticatedEncryptorDescriptorDeserializer, Microsoft.AspNetCore.DataProtection, Version=3.1.12.0, Culture=neutral, PublicKeyToken=adb9793829ddae60">
    <descriptor>
      <encryption algorithm="AES_256_CBC" />
      <validation algorithm="HMACSHA256" />
      <masterKey p4:requiresEncryption="true" xmlns:p4="http://schemas.asp.net/2015/03/dataProtection">
        <!-- Warning: the key below is in an unencrypted form. -->
        <value>dAgBW4UuUADgG5/+b6JsgOJX0MspQXLbqYmVdON6W3JE83kKCH3YuPtjBHhQPgDwM/5NIje5fwuG/Be+EYClDg==</value>
      </masterKey>
    </descriptor>
  </descriptor>
</key>